langchain_milvus/__init__.py
langchain_milvus/py.typed
langchain_milvus/retrievers/__init__.py
langchain_milvus/retrievers/milvus_hybrid_search.py
langchain_milvus/retrievers/zilliz_cloud_pipeline_retriever.py
langchain_milvus/utils/__init__.py
langchain_milvus/utils/sparse.py
langchain_milvus/vectorstores/__init__.py
langchain_milvus/vectorstores/milvus.py
langchain_milvus/vectorstores/zilliz.py
gigachain_milvus-0.1.4.dist-info/LICENSE
gigachain_milvus-0.1.4.dist-info/METADATA
gigachain_milvus-0.1.4.dist-info/WHEEL
gigachain_milvus-0.1.4.dist-info/RECORD
