Metadata-Version: 2.1
Name: gigachain-milvus
Version: 0.1.4
Summary: An integration package connecting Milvus and GigaChain
Home-page: https://github.com/ai-forever/gigachain
License: MIT
Requires-Python: >=3.8.1,<4.0
Classifier: License :: OSI Approved :: MIT License
Classifier: Programming Language :: Python :: 3
Classifier: Programming Language :: Python :: 3.9
Classifier: Programming Language :: Python :: 3.10
Classifier: Programming Language :: Python :: 3.11
Classifier: Programming Language :: Python :: 3.12
Requires-Dist: gigachain-core (>=0.2.20,<0.3.0)
Requires-Dist: pymilvus (>=2.4.3,<3.0.0)
Requires-Dist: scipy (>=1.7,<2.0) ; python_version < "3.12"
Requires-Dist: scipy (>=1.9,<2.0) ; python_version >= "3.12"
Project-URL: Repository, https://github.com/ai-forever/gigachain
Project-URL: Release Notes, https://github.com/ai-forever/gigachain/releases?q=tag%3A%22gigachain-milvus%3D%3D0%22&expanded=true
Project-URL: Source Code, https://github.com/ai-forever/gigachain/tree/master/libs/partners/milvus
